PyQPIC/__init__.py
PyQPIC/classes.py
PyQPIC/const.py
PyQPIC/deckgen.py
PyQPIC/get_bin.py
PyQPIC/readbeams.py
PyQPIC/tests/__init__.py
PyQPIC/tests/tests.py
PyQPIC-1.0a0.dev0.dist-info/DESCRIPTION.rst
PyQPIC-1.0a0.dev0.dist-info/METADATA
PyQPIC-1.0a0.dev0.dist-info/metadata.json
PyQPIC-1.0a0.dev0.dist-info/RECORD
PyQPIC-1.0a0.dev0.dist-info/top_level.txt
PyQPIC-1.0a0.dev0.dist-info/WHEEL
