Metadata-Version: 2.0
Name: PyQPIC
Version: 1.0a0.dev0
Summary: QuickPIC simulation control and data loading package
Home-page: https://github.com/joelfrederico/PyQPIC
Author: Joel Frederico, SLAC National Accelerator Laboratory
Author-email: joelfred@slac.stanford.edu
License: MIT
Keywords: analysis
Platform: UNKNOWN
Classifier: Development Status :: 3 - Alpha
Classifier: Intended Audience :: Science/Research
Classifier: Topic :: Scientific/Engineering :: Information Analysis
Classifier: License :: OSI Approved :: MIT License
Classifier: Programming Language :: Python :: 3
Classifier: Programming Language :: Python :: 3.4
Classifier: Programming Language :: Python :: 3 :: Only
Requires-Dist: numpy
Requires-Dist: SciSalt
